{
    "name": "@ohos/hidumper_lite",
    "description": "System information dump service for liteos-a kernel.",
    "optional": "false",
    "version": "3.1",
    "license": "Apache License 2.0",
    "publishAs": "code-segment",
    "segment": {
        "destPath": "base/hiviewdfx/hidumper_lite"
    },
    "dirs": {},
    "scripts": {},
    "component": {
        "name": "hidumper_lite",
        "subsystem": "hiviewdfx",
        "adapted_system_type": [
            "small"
        ],
        "rom": "26KB",
        "ram": "~10KB",
        "deps": {
            "components": [
            ],
            "third_party": [
                "cjson",
                "bounds_checking_function"
            ]
        },
        "build": {
            "sub_component": [
                "//base/hiviewdfx/hidumper_lite:hidumper"
            ]
        }
    }
}
